{
  "key": "USDMXN",
  "swap_type": "XCCY",
  "label": "USD/MXN NDS",
  "tenor": "5Y",
  "valuation_date": "2026-03-27",
  "par_rate": -16.759038,
  "metrics": {
    "BloombergDealID": "3000XRGZNMG1KAT9NM7WPC58R9Y49",
    "AccruedInterest": "0",
    "AsOfTimestamp": "2026-03-29T17:38:57.808",
    "DV01": "73659.83728512823",
    "DelayedEid": "",
    "ErrorCode": "0",
    "ErrorMessage": "",
    "MarketDataDate": "2026-03-27",
    "MktPx": "146.78562404107552",
    "MktVal": "140317955.87457767",
    "PV01": "83710.4244734832",
    "Position": "1",
    "RealtimeEid": "",
    "Security": "3000XRGZNMG1KAT9NM7WPC58R9Y49",
    "Ticker": "/NDS",
    "TrackingId": "6e326368-c372-4112-a85f-8e1c5263d155",
    "UniqueID": "CO",
    "ValuationDate": "2026-03-27"
  }
}